package/__init__.py
package/pgstoragelogger.py
pgstoragelogger-1.0.dist-info/LICENSE
pgstoragelogger-1.0.dist-info/METADATA
pgstoragelogger-1.0.dist-info/WHEEL
pgstoragelogger-1.0.dist-info/top_level.txt
pgstoragelogger-1.0.dist-info/RECORD
